[
  {
    "Directory": "C:\\Users\\AMD_GAMER\\OneDrive\\Documents//My Games//Tabletop Simulator//Mods//Workshop\\3551636229.json",
    "Name": "My cat Vasya",
    "UpdateTime": 1761512335
  },
  {
    "Directory": "C:\\Users\\AMD_GAMER\\OneDrive\\Documents//My Games//Tabletop Simulator//Mods//Workshop\\356805139.json",
    "Name": "Cards Against Humanity (With Expansions 1-5)",
    "UpdateTime": 1761512277
  },
  {
    "Directory": "C:\\Users\\AMD_GAMER\\OneDrive\\Documents//My Games//Tabletop Simulator//Mods//Workshop\\589767603.json",
    "Name": "Flash Point: Fire Rescue",
    "UpdateTime": 1761512276
  },
  {
    "Directory": "C:\\Users\\AMD_GAMER\\OneDrive\\Documents//My Games//Tabletop Simulator//Mods//Workshop\\672103781.json",
    "Name": "Flash Point: Fire Rescue scripted",
    "UpdateTime": 1761512275
  },
  {
    "Directory": "C:\\Users\\AMD_GAMER\\OneDrive\\Documents//My Games//Tabletop Simulator//Mods//Workshop\\860913280.json",
    "Name": "Dungeons and Dragons Boardgame + Expansions Full (English Ver.)",
    "UpdateTime": 1761512275
  },
  {
    "Directory": "C:\\Users\\AMD_GAMER\\OneDrive\\Documents//My Games//Tabletop Simulator//Mods//Workshop\\890238486.json",
    "Name": "Red Dragon Inn Room V 2.0",
    "UpdateTime": 1761512276
  }
]